xontrib/histcpy.py
xontrib_histcpy-0.1.dist-info/LICENSE
xontrib_histcpy-0.1.dist-info/METADATA
xontrib_histcpy-0.1.dist-info/WHEEL
xontrib_histcpy-0.1.dist-info/top_level.txt
xontrib_histcpy-0.1.dist-info/RECORD
