Metadata-Version: 2.1
Name: xontrib-histcpy
Version: 0.1
Summary: Useful aliases and shortcuts for extracting links and text from command output history in xonsh
Home-page: https://github.com/con-f-use/xontrib-histcpy
Author: con-f-use
Author-email: con-f-use@gmx.net
License: GPLv3
Platform: any
Classifier: Environment :: Console
Classifier: Intended Audience :: End Users/Desktop
Classifier: Operating System :: OS Independent
Classifier: Programming Language :: Python
Classifier: Topic :: Desktop Environment
Classifier: Topic :: System :: Shells
Classifier: Topic :: System :: System Shells
